Morpion/.DS_Store
Morpion/__main__.py
Morpion/datas.py
Morpion/dist/__main__/__main__
Morpion/dist/__main__/base_library.zip
Morpion/dist/__main__/certifi/cacert.pem
Morpion/dist/__main__/lib-dynload/_asyncio.cpython-39-darwin.so
Morpion/dist/__main__/lib-dynload/_bisect.cpython-39-darwin.so
Morpion/dist/__main__/lib-dynload/_blake2.cpython-39-darwin.so
Morpion/dist/__main__/lib-dynload/_bz2.cpython-39-darwin.so
Morpion/dist/__main__/lib-dynload/_codecs_cn.cpython-39-darwin.so
Morpion/dist/__main__/lib-dynload/_codecs_hk.cpython-39-darwin.so
Morpion/dist/__main__/lib-dynload/_codecs_iso2022.cpython-39-darwin.so
Morpion/dist/__main__/lib-dynload/_codecs_jp.cpython-39-darwin.so
Morpion/dist/__main__/lib-dynload/_codecs_kr.cpython-39-darwin.so
Morpion/dist/__main__/lib-dynload/_codecs_tw.cpython-39-darwin.so
Morpion/dist/__main__/lib-dynload/_contextvars.cpython-39-darwin.so
Morpion/dist/__main__/lib-dynload/_csv.cpython-39-darwin.so
Morpion/dist/__main__/lib-dynload/_ctypes.cpython-39-darwin.so
Morpion/dist/__main__/lib-dynload/_datetime.cpython-39-darwin.so
Morpion/dist/__main__/lib-dynload/_decimal.cpython-39-darwin.so
Morpion/dist/__main__/lib-dynload/_hashlib.cpython-39-darwin.so
Morpion/dist/__main__/lib-dynload/_heapq.cpython-39-darwin.so
Morpion/dist/__main__/lib-dynload/_json.cpython-39-darwin.so
Morpion/dist/__main__/lib-dynload/_lzma.cpython-39-darwin.so
Morpion/dist/__main__/lib-dynload/_md5.cpython-39-darwin.so
Morpion/dist/__main__/lib-dynload/_multibytecodec.cpython-39-darwin.so
Morpion/dist/__main__/lib-dynload/_multiprocessing.cpython-39-darwin.so
Morpion/dist/__main__/lib-dynload/_opcode.cpython-39-darwin.so
Morpion/dist/__main__/lib-dynload/_pickle.cpython-39-darwin.so
Morpion/dist/__main__/lib-dynload/_posixshmem.cpython-39-darwin.so
Morpion/dist/__main__/lib-dynload/_posixsubprocess.cpython-39-darwin.so
Morpion/dist/__main__/lib-dynload/_queue.cpython-39-darwin.so
Morpion/dist/__main__/lib-dynload/_random.cpython-39-darwin.so
morpion-0.5.1.dist-info/WHEEL
morpion-0.5.1.dist-info/METADATA
morpion-0.5.1.dist-info/RECORD
