Metadata-Version: 2.1
Name: morpion
Version: 0.5.1
Summary: A nice Morpion game
Author: PetchouHelper
Author-email: petchou91d@gmail.com
Requires-Python: >=3.9,<4.0
Classifier: Programming Language :: Python :: 3
Classifier: Programming Language :: Python :: 3.10
Classifier: Programming Language :: Python :: 3.9
Requires-Dist: art (>=5.2,<6.0)
Requires-Dist: requests (>=2.26.0,<3.0.0)
Requires-Dist: termcolor (>=1.1.0,<2.0.0)
